transport_tools/__init__.py
transport_tools/libs/__init__.py
transport_tools/libs/config.py
transport_tools/libs/geometry.py
transport_tools/libs/msms.py
transport_tools/libs/networks.py
transport_tools/libs/protein_files.py
transport_tools/libs/tools.py
transport_tools/libs/ui.py
transport_tools/libs/utils.py
transport_tools/scripts/__init__.py
transport_tools/scripts/tt_convert_to_caver.py
transport_tools/scripts/tt_engine.py
transport_tools/scripts/tt_filter_caver_by_frames.py
transport_tools/tests/__init__.py
transport_tools/tests/__main__.py
transport_tools/tests/integration/__init__.py
transport_tools/tests/integration/test_config.py
transport_tools/tests/integration/test_geometry.py
transport_tools/tests/integration/test_networks.py
transport_tools/tests/integration/test_protein_files.py
transport_tools/tests/integration/test_tools.py
transport_tools/tests/units/__init__.py
transport_tools/tests/units/test_geometry.py
transport_tools/tests/units/test_networks.py
transport_tools/tests/units/test_utils.py
transport_tools/tests/units/data/__init__.py
transport_tools/tests/units/data/data_geometry.py
transport_tools/tests/units/data/data_networks.py
transport_tools/tests/units/data/data_utils.py
transport_tools-0.9.5.data/scripts/tt_convert_to_caver.py
transport_tools-0.9.5.data/scripts/tt_engine.py
transport_tools-0.9.5.data/scripts/tt_filter_caver_by_frames.py
transport_tools-0.9.5.dist-info/METADATA
transport_tools-0.9.5.dist-info/WHEEL
transport_tools-0.9.5.dist-info/top_level.txt
transport_tools-0.9.5.dist-info/RECORD
