Metadata-Version: 2.1
Name: transport-tools
Version: 0.9.5
Summary: a library for massive analyses of internal voids in biomolecules and ligand transport through them
Home-page: http://labbit.eu/software
Author: Jan Brezovsky, Carlos Eduardo Sequeiros-Borja, Bartlomiej Surpeta
Author-email: janbre@amu.edu.pl
License: GNU GPL v3
Project-URL: Documentation, https://github.com/labbit-eu/transport_tools
Project-URL: Source, https://github.com/labbit-eu/transport_tools
Project-URL: Tracker, https://github.com/labbit-eu/transport_tools/issues
Keywords: molecular-dynamics transport tunnels channels
Classifier: Development Status :: 5 - Production/Stable
Classifier: Environment :: Console
Classifier: Intended Audience :: Science/Research
Classifier: Operating System :: POSIX
Classifier: Programming Language :: Python
Provides: transport_tools
Requires-Python: >=3.8
Requires-Dist: numpy (>=1.17.3)
Requires-Dist: scipy (>=1.5.2)
Requires-Dist: scikit-learn (>=0.24.0)
Requires-Dist: biopython (>=1.78)
Requires-Dist: fastcluster (>=1.1.25)
Requires-Dist: hdbscan (>=0.8.24)
Requires-Dist: mdtraj
Requires-Dist: threadpoolctl
Requires-Dist: joblib (<1.2.0)
